wawona/__init__.py
wawona/__main__.py
wawona/wawona.py
wawona-1.2.4.dist-info/LICENSE
wawona-1.2.4.dist-info/METADATA
wawona-1.2.4.dist-info/WHEEL
wawona-1.2.4.dist-info/entry_points.txt
wawona-1.2.4.dist-info/top_level.txt
wawona-1.2.4.dist-info/RECORD
