Metadata-Version: 2.1
Name: wawona
Version: 1.2.4
Summary: Easily make office reservations in sequoia from the command line.
Author-email: yuzawa-san <jtyuzawa+wawona@gmail.com>
License: MIT License
Project-URL: Homepage, https://github.com/yuzawa-san/wawona
Project-URL: Changelog, https://github.com/yuzawa-san/wawona/releases
Project-URL: Issues, https://github.com/yuzawa-san/wawona/issues
Project-URL: CI, https://github.com/yuzawa-san/wawona/actions
Project-URL: Documentation, https://github.com/yuzawa-san/wawona/blob/master/README.md
Project-URL: Repository, https://github.com/yuzawa-san/wawona.git
Project-URL: Funding, http://paypal.me/yuzawasan
Classifier: License :: OSI Approved :: MIT License
Classifier: Programming Language :: Python :: 3.8
Classifier: Operating System :: OS Independent
Classifier: Environment :: Console
Requires-Python: >=3.8
License-File: LICENSE
Requires-Dist: requests ==2.32.3
Requires-Dist: inquirer ==3.3.0
Requires-Dist: texttable ==1.7.0
Requires-Dist: pytz ==2024.1
Requires-Dist: selenium ==4.23.1
